sapiens_attention/__init__.py
sapiens_attention/sapiens_attention.py
sapiens_attention-1.0.7.dist-info/LICENSE.txt
sapiens_attention-1.0.7.dist-info/METADATA
sapiens_attention-1.0.7.dist-info/WHEEL
sapiens_attention-1.0.7.dist-info/top_level.txt
sapiens_attention-1.0.7.dist-info/RECORD
