Metadata-Version: 2.2
Name: sapiens_attention
Version: 1.0.7
Home-page: https://github.com/sapiens-technology/SapiensAttention
Author: SAPIENS TECHNOLOGY
License: Proprietary Software
License-File: LICENSE.txt
Requires-Dist: langdetect
Requires-Dist: yake
Dynamic: author
Dynamic: home-page
Dynamic: license
Dynamic: requires-dist
